tdhook/__init__.py
tdhook/artifacts.py
tdhook/contexts.py
tdhook/hooks.py
tdhook/metrics.py
tdhook/module.py
tdhook/acteng/__init__.py
tdhook/acteng/activation_caching.py
tdhook/acteng/activation_patching.py
tdhook/acteng/linear_probing.py
tdhook/acteng/steering_vectors.py
tdhook/attribution/__init__.py
tdhook/attribution/grad_cam.py
tdhook/attribution/layer_feature_ablation.py
tdhook/attribution/neuron_gradient.py
tdhook/attribution/occlusion.py
tdhook/attribution/gradient_attribution/__init__.py
tdhook/attribution/gradient_attribution/common.py
tdhook/attribution/gradient_attribution/helpers.py
tdhook/attribution/gradient_attribution/integrated_gradients.py
tdhook/attribution/gradient_attribution/saliency.py
tdhook/attribution/lrp/__init__.py
tdhook/attribution/lrp/layers.py
tdhook/attribution/lrp/lrp.py
tdhook/attribution/lrp/rules.py
tdhook/attribution/lrp/types.py
tdhook/auto/__init__.py
tdhook/weights/__init__.py
tdhook/weights/task_vectors.py
tdhook-0.1.1.dist-info/licenses/LICENSE
tdhook-0.1.1.dist-info/METADATA
tdhook-0.1.1.dist-info/WHEEL
tdhook-0.1.1.dist-info/top_level.txt
tdhook-0.1.1.dist-info/RECORD
