Metadata-Version: 2.4
Name: tdhook
Version: 0.1.1
Summary: Interpretability with tensordict and torch hooks.
Author-email: Yoann Poupart <yoann.poupart@ens-lyon.org>
License: MIT License
Project-URL: homepage, https://tdhook.readthedocs.io/
Project-URL: documentation, https://tdhook.readthedocs.io/
Project-URL: source, https://github.com/Xmaster6y/tdhook
Project-URL: issues, https://github.com/Xmaster6y/tdhook/issues
Project-URL: releasenotes, https://github.com/Xmaster6y/tdhook/releases
Classifier: Development Status :: 3 - Alpha
Classifier: Intended Audience :: Science/Research
Classifier: Programming Language :: Python :: 3
Classifier: Programming Language :: Python :: 3.11
Classifier: Programming Language :: Python :: 3.12
Requires-Python: >=3.11
License-File: LICENSE
Requires-Dist: tensordict>=0.9.1
Requires-Dist: torch>=2.7.1
Dynamic: license-file
